{
  "nextUID": 19,
  "Jurors": {
    "0": {
      "JuryID": 0,
      "firstName": "Barry",
      "lastName": "Allan",
      "address1": "3043 Gorby Lane",
      "address2": "Appling, GA 30802",
      "phone": "804-954-3051",
      "email": "Barry.Allan@gmail.com",
      "canText": false,
      "receiveCall": true,
      "receiveEmail": true,
      "receiveText": false,
      "registrationStatus": "new",
      "deferCount": 0,
      "password": "",
      "surveyResponses": []
    },
    "1": {
      "JuryID": 1,
      "firstName": "Slade",
      "lastName": "Wilson",
      "address1": "2654 Buckhannan Avenue",
      "address2": "Richmond, VA 23220",
      "phone": "832-593-2084",
      "email": "Slade.Wilson@gmail.com",
      "canText": false,
      "receiveCall": false,
      "receiveEmail": true,
      "receiveText": true,
      "registrationStatus": "new",
      "deferCount": 0,
      "password": "",
      "surveyResponses": []
    },
    "2": {
      "JuryID": 2,
      "firstName": "Clark",
      "lastName": "Kent",
      "address1": "1253 Melody Lane",
      "address2": "Breese, IL 62230",
      "phone": "832-593-2084",
      "email": "Clark.Kent@gmail.com",
      "canText": false,
      "receiveCall": true,
      "receiveEmail": true,
      "receiveText": true,
      "registrationStatus": "new",
      "deferCount": 0,
      "password": "",
      "surveyResponses": []
    },
    "3": {
      "JuryID": 3,
      "firstName": "Bruce",
      "lastName": "Wayne",
      "address1": "1253 Melody Lane",
      "address2": "Breese, IL 62230",
      "phone": "412-665-4666",
      "email": "Bruce.Wayne@gmail.com",
      "canText": false,
      "receiveCall": true,
      "receiveEmail": true,
      "receiveText": false,
      "registrationStatus": "new",
      "deferCount": 0,
      "password": "",
      "surveyResponses": []
    },
    "4": {
      "JuryID": 4,
      "firstName": "Peter",
      "lastName": "Parker",
      "address1": "3043 Gorby Lane",
      "address2": "Appling, GA 30802",
      "phone": "361-331-4809",
      "email": "Peter.Parker@gmail.com",
      "canText": true,
      "receiveCall": true,
      "receiveEmail": false,
      "receiveText": true,
      "registrationStatus": "new",
      "deferCount": 0,
      "password": "",
      "surveyResponses": []
    },
    "5": {
      "JuryID": 5,
      "firstName": "Tony",
      "lastName": "Stark",
      "address1": "4802 Butternut Lane",
      "address2": "Syracuse, NY 13202",
      "phone": "412-665-4666",
      "email": "Tony.Stark@gmail.com",
      "canText": true,
      "receiveCall": true,
      "receiveEmail": true,
      "receiveText": true,
      "registrationStatus": "new",
      "deferCount": 0,
      "password": "",
      "surveyResponses": []
    },
    "6": {
      "JuryID": 6,
      "firstName": "Howard",
      "lastName": "Stark",
      "address1": "3043 Gorby Lane",
      "address2": "Jackson, MS 39201",
      "phone": "832-593-2084",
      "email": "Howard.Stark@gmail.com",
      "canText": true,
      "receiveCall": true,
      "receiveEmail": false,
      "receiveText": false,
      "registrationStatus": "new",
      "deferCount": 0,
      "password": "",
      "surveyResponses": []
    },
    "7": {
      "JuryID": 7,
      "firstName": "Jarvis",
      "lastName": "Stark",
      "address1": "2654 Buckhannan Avenue",
      "address2": "Fresno, CA 93721",
      "phone": "903-388-4065",
      "email": "Jarvis.Stark@gmail.com",
      "canText": false,
      "receiveCall": false,
      "receiveEmail": false,
      "receiveText": false,
      "registrationStatus": "new",
      "deferCount": 0,
      "password": "",
      "surveyResponses": []
    },
    "8": {
      "JuryID": 8,
      "firstName": "Malcom",
      "lastName": "Merlin",
      "address1": "2625 Simpson Street",
      "address2": "Cicero, NY 13039",
      "phone": "804-954-3051",
      "email": "Malcom.Merlin@gmail.com",
      "canText": true,
      "receiveCall": true,
      "receiveEmail": true,
      "receiveText": true,
      "registrationStatus": "new",
      "deferCount": 0,
      "password": "",
      "surveyResponses": []
    },
    "9": {
      "JuryID": 9,
      "firstName": "Ray",
      "lastName": "Palmer",
      "address1": "4802 Butternut Lane",
      "address2": "Breese, IL 62230",
      "phone": "804-954-3051",
      "email": "Ray.Palmer@gmail.com",
      "canText": true,
      "receiveCall": false,
      "receiveEmail": true,
      "receiveText": true,
      "registrationStatus": "new",
      "deferCount": 0,
      "password": "",
      "surveyResponses": []
    },
    "10": {
      "JuryID": 10,
      "firstName": "Oliver",
      "lastName": "Queen",
      "address1": "103 Edgewood Avenue",
      "address2": "Jackson, MS 39201",
      "phone": "612-877-4529",
      "email": "Oliver.Queen@gmail.com",
      "canText": true,
      "receiveCall": true,
      "receiveEmail": false,
      "receiveText": true,
      "registrationStatus": "new",
      "deferCount": 0,
      "password": "",
      "surveyResponses": []
    },
    "11": {
      "JuryID": 11,
      "firstName": "Perry",
      "lastName": "White",
      "address1": "1176 Hart Country Lane",
      "address2": "Appling, GA 30802",
      "phone": "907-943-5083",
      "email": "Perry.White@gmail.com",
      "canText": false,
      "receiveCall": true,
      "receiveEmail": true,
      "receiveText": false,
      "registrationStatus": "new",
      "deferCount": 0,
      "password": "",
      "surveyResponses": []
    },
    "12": {
      "JuryID": 12,
      "firstName": "Bruce",
      "lastName": "Banner",
      "address1": "2625 Simpson Street",
      "address2": "Fresno, CA 93721",
      "phone": "832-593-2084",
      "email": "Bruce.Banner@gmail.com",
      "canText": false,
      "receiveCall": true,
      "receiveEmail": false,
      "receiveText": true,
      "registrationStatus": "new",
      "deferCount": 0,
      "password": "",
      "surveyResponses": []
    },
    "13": {
      "JuryID": 13,
      "firstName": "Wade",
      "lastName": "Wilson",
      "address1": "103 Edgewood Avenue",
      "address2": "Cicero, NY 13039",
      "phone": "832-593-2084",
      "email": "Wade.Wilson@gmail.com",
      "canText": false,
      "receiveCall": false,
      "receiveEmail": true,
      "receiveText": true,
      "registrationStatus": "new",
      "deferCount": 0,
      "password": "",
      "surveyResponses": []
    },
    "14": {
      "JuryID": 14,
      "firstName": "Natasha",
      "lastName": "Banner",
      "address1": "4802 Butternut Lane",
      "address2": "Fresno, CA 93721",
      "phone": "832-593-2084",
      "email": "Natasha.Banner@gmail.com",
      "canText": false,
      "receiveCall": true,
      "receiveEmail": false,
      "receiveText": false,
      "registrationStatus": "new",
      "deferCount": 0,
      "password": "",
      "surveyResponses": []
    },
    "15": {
      "JuryID": 15,
      "firstName": "Risa",
      "lastName": "Hawkeye",
      "address1": "1253 Melody Lane",
      "address2": "Fresno, CA 93721",
      "phone": "804-954-3051",
      "email": "Risa.Hawkeye@gmail.com",
      "canText": true,
      "receiveCall": false,
      "receiveEmail": false,
      "receiveText": true,
      "registrationStatus": "new",
      "deferCount": 0,
      "password": "",
      "surveyResponses": []
    },
    "16": {
      "JuryID": 16,
      "firstName": "Edward",
      "lastName": "Elrich",
      "address1": "2654 Buckhannan Avenue",
      "address2": "Fresno, CA 93721",
      "phone": "612-877-4529",
      "email": "Edward.Elrich@gmail.com",
      "canText": false,
      "receiveCall": true,
      "receiveEmail": true,
      "receiveText": false,
      "registrationStatus": "new",
      "deferCount": 0,
      "password": "",
      "surveyResponses": []
    },
    "17": {
      "JuryID": 17,
      "firstName": "Alfonse",
      "lastName": "Elrich",
      "address1": "103 Edgewood Avenue",
      "address2": "Syracuse, NY 13202",
      "phone": "903-388-4065",
      "email": "Alfonse.Elrich@gmail.com",
      "canText": false,
      "receiveCall": true,
      "receiveEmail": false,
      "receiveText": true,
      "registrationStatus": "new",
      "deferCount": 0,
      "password": "",
      "surveyResponses": []
    },
    "18": {
      "JuryID": 18,
      "firstName": "Akihiko",
      "lastName": "Kayaba",
      "address1": "4802 Butternut Lane",
      "address2": "Little York, IL 61453",
      "phone": "832-593-2084",
      "email": "Akihiko.Kayaba@gmail.com",
      "canText": false,
      "receiveCall": false,
      "receiveEmail": false,
      "receiveText": false,
      "registrationStatus": "new",
      "deferCount": 0,
      "password": "",
      "surveyResponses": []
    }
  }
}